{
    "key": "group_645b865962156",
    "title": "Layout - Text Center",
    "fields": [
        {
            "key": "field_645b86597adcb",
            "label": "Content Settings",
            "name": "",
            "aria-label": "",
            "type": "tab",
            "instructions": "",
            "required": 0,
            "conditional_logic": 0,
            "wrapper": {
                "width": "",
                "class": "",
                "id": ""
            },
            "placement": "top",
            "endpoint": 0
        },
        {
            "key": "field_645b86597ade0",
            "label": "Section Intro",
            "name": "section_intro",
            "aria-label": "",
            "type": "group",
            "instructions": "",
            "required": 0,
            "conditional_logic": 0,
            "wrapper": {
                "width": "",
                "class": "label-hidden",
                "id": ""
            },
            "acfe_save_meta": 0,
            "layout": "row",
            "acfe_seamless_style": 0,
            "acfe_group_modal": 0,
            "acfe_settings": "",
            "acfe_permissions": "",
            "acfe_group_modal_close": 0,
            "acfe_group_modal_button": "",
            "acfe_group_modal_size": "large",
            "sub_fields": [
                {
                    "key": "field_645b865981dbe",
                    "label": "Sub Headline",
                    "name": "sub_headline",
                    "aria-label": "",
                    "type": "text",
                    "instructions": "",
                    "required": 0,
                    "conditional_logic": 0,
                    "wrapper": {
                        "width": "",
                        "class": "",
                        "id": ""
                    },
                    "acfe_save_meta": 0,
                    "default_value": "",
                    "acfe_settings": "",
                    "acfe_validate": "",
                    "maxlength": "",
                    "acfe_permissions": "",
                    "placeholder": "",
                    "prepend": "",
                    "append": ""
                },
                {
                    "key": "field_645b865981dcc",
                    "label": "Headline",
                    "name": "headline",
                    "aria-label": "",
                    "type": "text",
                    "instructions": "",
                    "required": 0,
                    "conditional_logic": 0,
                    "wrapper": {
                        "width": "",
                        "class": "",
                        "id": ""
                    },
                    "default_value": "",
                    "acfe_settings": "",
                    "acfe_validate": "",
                    "maxlength": "",
                    "placeholder": "",
                    "prepend": "",
                    "append": ""
                },
                {
                    "key": "field_645b92954ade3",
                    "label": "Lead Text",
                    "name": "lead_text",
                    "aria-label": "",
                    "type": "clone",
                    "instructions": "",
                    "required": 0,
                    "conditional_logic": 0,
                    "wrapper": {
                        "width": "",
                        "class": "",
                        "id": ""
                    },
                    "acfe_save_meta": 0,
                    "clone": [
                        "group_62a2107ccfb06"
                    ],
                    "display": "group",
                    "layout": "block",
                    "prefix_label": 0,
                    "prefix_name": 0,
                    "acfe_seamless_style": 0,
                    "acfe_clone_modal": 0,
                    "acfe_settings": "",
                    "acfe_permissions": "",
                    "acfe_clone_modal_close": 0,
                    "acfe_clone_modal_button": "",
                    "acfe_clone_modal_size": "large"
                }
            ]
        },
        {
            "key": "field_645b87034cc28",
            "label": "Content",
            "name": "content",
            "aria-label": "",
            "type": "clone",
            "instructions": "",
            "required": 0,
            "conditional_logic": 0,
            "wrapper": {
                "width": "",
                "class": "",
                "id": ""
            },
            "acfe_save_meta": 0,
            "clone": [
                "group_62a2107ccfb06"
            ],
            "display": "group",
            "layout": "block",
            "prefix_label": 0,
            "prefix_name": 0,
            "acfe_seamless_style": 0,
            "acfe_clone_modal": 0,
            "acfe_settings": "",
            "acfe_permissions": "",
            "acfe_clone_modal_close": 0,
            "acfe_clone_modal_button": "",
            "acfe_clone_modal_size": "large"
        },
        {
            "key": "field_645b86597add8",
            "label": "Section Intro",
            "name": "",
            "aria-label": "",
            "type": "accordion",
            "instructions": "",
            "required": 0,
            "conditional_logic": 0,
            "wrapper": {
                "width": "",
                "class": "",
                "id": ""
            },
            "open": 0,
            "multi_expand": 0,
            "endpoint": 0,
            "acfe_permissions": ""
        },
        {
            "key": "field_645b86597ade8",
            "label": "Accordion",
            "name": "",
            "aria-label": "",
            "type": "accordion",
            "instructions": "",
            "required": 0,
            "conditional_logic": 0,
            "wrapper": {
                "width": "",
                "class": "",
                "id": ""
            },
            "open": 0,
            "multi_expand": 0,
            "endpoint": 0,
            "acfe_permissions": ""
        },
        {
            "key": "field_645b86597adfc",
            "label": "Background",
            "name": "",
            "aria-label": "",
            "type": "accordion",
            "instructions": "",
            "required": 0,
            "conditional_logic": 0,
            "wrapper": {
                "width": "",
                "class": "",
                "id": ""
            },
            "open": 0,
            "multi_expand": 0,
            "endpoint": 0,
            "acfe_permissions": ""
        },
        {
            "key": "field_645b86597ae09",
            "label": "Background",
            "name": "background",
            "aria-label": "",
            "type": "group",
            "instructions": "",
            "required": 0,
            "conditional_logic": 0,
            "wrapper": {
                "width": "",
                "class": "",
                "id": ""
            },
            "acfe_save_meta": 0,
            "layout": "block",
            "acfe_seamless_style": 0,
            "acfe_group_modal": 0,
            "acfe_settings": "",
            "acfe_permissions": "",
            "acfe_group_modal_close": 0,
            "acfe_group_modal_button": "",
            "acfe_group_modal_size": "large",
            "sub_fields": [
                {
                    "key": "field_645b865996f9a",
                    "label": "Background Image",
                    "name": "background_image",
                    "aria-label": "",
                    "type": "image",
                    "instructions": "",
                    "required": 0,
                    "conditional_logic": 0,
                    "wrapper": {
                        "width": "33.33",
                        "class": "",
                        "id": ""
                    },
                    "acfe_save_meta": 0,
                    "uploader": "",
                    "return_format": "array",
                    "acfe_thumbnail": 0,
                    "acfe_settings": "",
                    "acfe_validate": "",
                    "min_width": "",
                    "min_height": "",
                    "min_size": "",
                    "max_width": "",
                    "max_height": "",
                    "max_size": "",
                    "mime_types": "",
                    "preview_size": "medium",
                    "library": "all"
                },
                {
                    "key": "field_645b865996fad",
                    "label": "Background Color",
                    "name": "background_color",
                    "aria-label": "",
                    "type": "color_picker",
                    "instructions": "",
                    "required": 0,
                    "conditional_logic": 0,
                    "wrapper": {
                        "width": "33.33",
                        "class": "",
                        "id": ""
                    },
                    "acfe_save_meta": 0,
                    "default_value": "#1068F0",
                    "enable_opacity": 0,
                    "return_format": "string",
                    "acfe_settings": "",
                    "acfe_validate": "",
                    "acfe_permissions": ""
                },
                {
                    "key": "field_645b865996fbc",
                    "label": "Text Color",
                    "name": "text_color",
                    "aria-label": "",
                    "type": "select",
                    "instructions": "",
                    "required": 0,
                    "conditional_logic": 0,
                    "wrapper": {
                        "width": "33.33",
                        "class": "",
                        "id": ""
                    },
                    "acfe_save_meta": 0,
                    "choices": {
                        "default": "Default",
                        "white": "White"
                    },
                    "default_value": "white",
                    "return_format": "value",
                    "multiple": 0,
                    "acfe_settings": "",
                    "acfe_validate": "",
                    "allow_null": 0,
                    "acfe_permissions": "",
                    "ui": 0,
                    "ajax": 0,
                    "placeholder": "",
                    "allow_custom": 0,
                    "search_placeholder": ""
                }
            ]
        },
        {
            "key": "field_645b86597ae14",
            "label": "Accordion End Point",
            "name": "",
            "aria-label": "",
            "type": "accordion",
            "instructions": "",
            "required": 0,
            "conditional_logic": 0,
            "wrapper": {
                "width": "",
                "class": "",
                "id": ""
            },
            "open": 0,
            "multi_expand": 0,
            "endpoint": 1,
            "acfe_permissions": ""
        },
        {
            "key": "field_645b86597ae1d",
            "label": "Section Settings",
            "name": "",
            "aria-label": "",
            "type": "tab",
            "instructions": "",
            "required": 0,
            "conditional_logic": 0,
            "wrapper": {
                "width": "",
                "class": "",
                "id": ""
            },
            "placement": "top",
            "endpoint": 0
        },
        {
            "key": "field_645b86597ae25",
            "label": "Section Settings",
            "name": "section_settings",
            "aria-label": "",
            "type": "clone",
            "instructions": "",
            "required": 0,
            "conditional_logic": 0,
            "wrapper": {
                "width": "",
                "class": "",
                "id": ""
            },
            "clone": [
                "group_629ecb2c781f6"
            ],
            "display": "group",
            "layout": "row",
            "prefix_label": 0,
            "prefix_name": 0,
            "acfe_seamless_style": 1,
            "acfe_clone_modal": 0,
            "acfe_clone_modal_close": 0,
            "acfe_clone_modal_button": "",
            "acfe_clone_modal_size": "large"
        }
    ],
    "location": [
        [
            {
                "param": "post_type",
                "operator": "==",
                "value": "page"
            }
        ]
    ],
    "menu_order": 0,
    "position": "normal",
    "style": "default",
    "label_placement": "top",
    "instruction_placement": "field",
    "hide_on_screen": "",
    "active": false,
    "description": "",
    "show_in_rest": 0,
    "acfe_display_title": "",
    "acfe_autosync": [
        "json"
    ],
    "acfe_permissions": "",
    "acfe_form": 1,
    "acfe_meta": "",
    "acfe_note": "",
    "modified": 1683722925,
    "acfe_categories": {
        "layout": "Layout"
    }
}